dictionarysort/__init__.py
dictionarysort/dictionarysort.py
dictionarysort-1.1.0.dist-info/LICENSE
dictionarysort-1.1.0.dist-info/METADATA
dictionarysort-1.1.0.dist-info/WHEEL
dictionarysort-1.1.0.dist-info/top_level.txt
dictionarysort-1.1.0.dist-info/RECORD
