Metadata-Version: 2.1
Name: dictionarysort
Version: 1.1.0
Summary: A package to sort python dictionary
Author-email: Sharad Jadham <sharad.jadham@gmail.com>
Project-URL: Homepage, https://github.com/pypa/sampleproject
Project-URL: Bug Tracker, https://github.com/pypa/sampleproject/issues
Classifier: Programming Language :: Python :: 3
Classifier: License :: OSI Approved :: MIT License
Classifier: Operating System :: OS Independent
Requires-Python: >=2.7
License-File: LICENSE
